microframework/__init__.py
microframework/handler.py
microframework/models.py
microframework/sender.py
microframework/utils.py
microframework/management/__init__.py
microframework/management/commands/__init__.py
microframework/management/commands/run_listener.py
microframework/migrations/0001_initial.py
microframework/migrations/__init__.py
django_microframework-0.1.0.dist-info/LICENSE.md
django_microframework-0.1.0.dist-info/METADATA
django_microframework-0.1.0.dist-info/WHEEL
django_microframework-0.1.0.dist-info/top_level.txt
django_microframework-0.1.0.dist-info/RECORD
